sage_meta/__init__.py
sage_meta/models/__init__.py
sage_meta/models/data.py
sage_meta/service/__init__.py
sage_meta/service/base.py
sage_meta/service/content.py
sage_meta/service/copyright.py
sage_meta/service/handlers/__init__.py
sage_meta/service/handlers/comment.py
sage_meta/service/handlers/hashtag.py
sage_meta/service/handlers/media.py
sage_meta/service/handlers/stories.py
sage_meta/service/handlers/user.py
sage_meta/service/product.py
python_sage_meta-0.1.0.dist-info/LICENSE
python_sage_meta-0.1.0.dist-info/METADATA
python_sage_meta-0.1.0.dist-info/WHEEL
python_sage_meta-0.1.0.dist-info/RECORD
