Metadata-Version: 2.1
Name: python-sage-meta
Version: 0.1.0
Summary: A python package for managing Meta GraphQL API.
Home-page: https://github.com/sageteamorg/python-sage-meta
License: MIT
Keywords: python,facebook-api,facebook,meta,python-packages
Author: radin qahremani
Author-email: radin@sageteam.org
Requires-Python: >=3.11,<4.0
Classifier: Intended Audience :: Developers
Classifier: License :: OSI Approved :: MIT License
Classifier: Operating System :: OS Independent
Classifier: Programming Language :: Python :: 3
Classifier: Programming Language :: Python :: 3.11
Classifier: Programming Language :: Python :: 3.12
Requires-Dist: facebook-sdk (>=3.1.0,<4.0.0)
Requires-Dist: python-dotenv (>=1.0.1,<2.0.0)
Requires-Dist: requests (>=2.32.3,<3.0.0)
Project-URL: Documentation, https://python-sage-meta.readthedocs.io/en/latest/
Project-URL: Issues, https://github.com/sageteamorg/python-sage-meta/issues
Project-URL: Repository, https://github.com/sageteamorg/python-sage-meta
Project-URL: Source Code, https://github.com/sageteamorg/python-sage-meta
